html5routes/__init__.py
html5routes-0.0.2.dist-info/METADATA
html5routes-0.0.2.dist-info/WHEEL
html5routes-0.0.2.dist-info/entry_points.txt
html5routes-0.0.2.dist-info/top_level.txt
html5routes-0.0.2.dist-info/RECORD
